jupyter_progressbar
